flameboi/__init__.py
flameboi/__main__.py
flameboi/app.py
flameboi/blocks/__init__.py
flameboi/blocks/block.py
flameboi/blocks/block_generator.py
flameboi/blocks/block_element/__init__.py
flameboi/blocks/block_element/block_element.py
flameboi/blocks/block_element/button_element.py
flameboi/blocks/block_element/datepicker_element.py
flameboi/blocks/block_element/image_element.py
flameboi/blocks/block_element/overflow_element.py
flameboi/blocks/block_element/plain_text_input_element.py
flameboi/blocks/block_element/radio_button_group_element.py
flameboi/blocks/composition_object/__init__.py
flameboi/blocks/composition_object/confirm_object.py
flameboi/blocks/composition_object/option_group_object.py
flameboi/blocks/composition_object/option_object.py
flameboi/blocks/composition_object/text_object.py
flameboi/blocks/interactive_component/__init__.py
flameboi/blocks/layout_block/__init__.py
flameboi/blocks/layout_block/actions_block.py
flameboi/blocks/layout_block/context_block.py
flameboi/blocks/layout_block/divider_block.py
flameboi/blocks/layout_block/file_block.py
flameboi/blocks/layout_block/image_block.py
flameboi/blocks/layout_block/input_block.py
flameboi/blocks/layout_block/layout_block.py
flameboi/blocks/layout_block/section_block.py
flameboi/blocks/view_payload/__init__.py
flameboi/blocks/view_payload/view_payload.py
flameboi/common/IEvent.py
flameboi/common/__init__.py
flameboi/common/flameboi.py
flameboi/common/routing.py
flameboi/events/__init__.py
flameboi/events/app_mention_event.py
flameboi/events/channel_join_event.py
flameboi/events/message_event.py
flameboi/events/pin_added_event.py
flameboi/events/reaction_added_event.py
flameboi/events/slash_command.py
flameboi/events/team_join_event.py
flameboi/modules/__init__.py
flameboi/modules/corona.py
flameboi/modules/dice.py
flameboi/modules/fah.py
flameboi/modules/onboard.py
flameboi/modules/playlists.py
flameboi/modules/qod.py
Flameboi-0.0.2.dev0.dist-info/LICENSE
Flameboi-0.0.2.dev0.dist-info/METADATA
Flameboi-0.0.2.dev0.dist-info/WHEEL
Flameboi-0.0.2.dev0.dist-info/top_level.txt
Flameboi-0.0.2.dev0.dist-info/RECORD
