Metadata-Version: 2.1
Name: Flameboi
Version: 0.0.2.dev0
Summary: Slack chat bot
Home-page: https://github.com/ASU-CodeDevils/flameboi-slack-api
Author: CodeDevil's Student Organization
Author-email: stucampbell.git@gmail.com
License: MIT License
Platform: UNKNOWN
Classifier: Topic :: Communications
Classifier: Topic :: Communications :: Chat
Classifier: Topic :: Internet :: WWW/HTTP :: WSGI
Classifier: Topic :: Internet :: WWW/HTTP :: WSGI :: Application
Classifier: Development Status :: 2 - Pre-Alpha
Classifier: Environment :: Web Environment
Classifier: Framework :: Flask
Classifier: License :: OSI Approved :: MIT License
Classifier: Programming Language :: Python :: 3.8
Requires-Python: >=3.8
Requires-Dist: Flask
Requires-Dist: python-dotenv
Requires-Dist: requests
Requires-Dist: slack
Requires-Dist: slackclient
Requires-Dist: slackeventsapi
